filesh/__init__.py
filesh/__main__.py
filesh/server.py
filesh-1.2.0.dist-info/METADATA
filesh-1.2.0.dist-info/WHEEL
filesh-1.2.0.dist-info/entry_points.txt
filesh-1.2.0.dist-info/licenses/LICENSE
filesh-1.2.0.dist-info/RECORD
