Metadata-Version: 2.4
Name: filesh
Version: 1.2.0
Summary: Simple and modern LAN file sharing server with web UI
Author: Kutay Koca
License-Expression: MIT
License-File: LICENSE
Keywords: download,file-server,file-sharing,http-server,lan,local-network,upload,web-ui
Classifier: Development Status :: 5 - Production/Stable
Classifier: Environment :: Console
Classifier: Environment :: Web Environment
Classifier: Intended Audience :: Developers
Classifier: Intended Audience :: End Users/Desktop
Classifier: License :: OSI Approved :: MIT License
Classifier: Operating System :: OS Independent
Classifier: Programming Language :: Python :: 3
Classifier: Programming Language :: Python :: 3.8
Classifier: Programming Language :: Python :: 3.9
Classifier: Programming Language :: Python :: 3.10
Classifier: Programming Language :: Python :: 3.11
Classifier: Programming Language :: Python :: 3.12
Classifier: Topic :: Internet :: WWW/HTTP :: HTTP Servers
Classifier: Topic :: System :: Networking
Classifier: Topic :: Utilities
Requires-Python: >=3.8
Requires-Dist: flask>=2.0.0
Requires-Dist: qrcode>=7.0
